mini_react-0.1.2.dist-info/licenses/LICENSE
minireact/__init__.py
minireact/lm.py
minireact/module.py
minireact/predict.py
minireact/prompt.py
minireact/prompt_zh.py
minireact/react.py
minireact/signature.py
minireact/streamify.py
minireact/tool.py
mini_react-0.1.2.dist-info/METADATA
mini_react-0.1.2.dist-info/WHEEL
mini_react-0.1.2.dist-info/top_level.txt
mini_react-0.1.2.dist-info/RECORD
