Metadata-Version: 2.4
Name: mini-react
Version: 0.1.2
Summary: mini-react 轻量级的 ReAct（Reasoning and Acting）智能体框架
Author-email: jiulang <thisgame@foxmail.com>
Project-URL: Homepage, https://github.com/cottagephilosopher/mini-react
License-File: LICENSE
Dynamic: license-file
